korean_geocoding/__init__.py
korean_geocoding/common.py
korean_geocoding/converter.py
korean_geocoding/geocoding.py
korean_geocoding/naver_gc_api.py
korean_geocoding/section.py
korean_geocoding/sido_dict.py
korean_geocoding/data/Busan.dat
korean_geocoding/data/Daegu.dat
korean_geocoding/data/Daejeon.dat
korean_geocoding/data/Gangwon.dat
korean_geocoding/data/Gwangju.dat
korean_geocoding/data/Gyeonggi.dat
korean_geocoding/data/Incheon.dat
korean_geocoding/data/Jeju.dat
korean_geocoding/data/NorthChungcheong.dat
korean_geocoding/data/NorthGyeongsang.dat
korean_geocoding/data/NorthJeolla.dat
korean_geocoding/data/Sejong.dat
korean_geocoding/data/Seoul.dat
korean_geocoding/data/SouthChungcheong.dat
korean_geocoding/data/SouthGyeongsang.dat
korean_geocoding/data/SouthJeolla.dat
korean_geocoding/data/Ulsan.dat
korean_geocoding/data/__init__.py
korean_geocoding-0.4.1.dist-info/LICENSE
korean_geocoding-0.4.1.dist-info/METADATA
korean_geocoding-0.4.1.dist-info/WHEEL
korean_geocoding-0.4.1.dist-info/top_level.txt
korean_geocoding-0.4.1.dist-info/RECORD
