Metadata-Version: 2.1
Name: korean-geocoding
Version: 0.4.1
Summary: Korean geocoding library with Naver Geocoding API
Home-page: https://github.com/RE-A/korean-geocoding
Author: RE-A
Author-email: skynine73@gmail.com
License: UNKNOWN
Platform: UNKNOWN
Requires-Python: >=3.8
License-File: LICENSE
Requires-Dist: requests
Requires-Dist: haversine
Requires-Dist: pyproj
